rbautoml/__init__.py
rbautoml/rbautoml_functions.py
rbautoml-1.1.0.dist-info/LICENSE
rbautoml-1.1.0.dist-info/METADATA
rbautoml-1.1.0.dist-info/WHEEL
rbautoml-1.1.0.dist-info/top_level.txt
rbautoml-1.1.0.dist-info/RECORD
