Metadata-Version: 2.1
Name: rbautoml
Version: 1.1.0
Summary: Convenience library for interacting with the Rainbird AutoML Rest API Tool
Author-email: Nathan Roberts <nathan.roberts@rainbird.ai>
Project-URL: Homepage, https://rainbird.ai/platform/
Keywords: machine,learning,automl
Classifier: License :: OSI Approved :: MIT License
Classifier: Programming Language :: Python :: 3
Requires-Python: >=3.7
License-File: LICENSE
Requires-Dist: httpx (>=0.22.0)
Provides-Extra: dev
Requires-Dist: numpy ; extra == 'dev'
Requires-Dist: pandas ; extra == 'dev'
